cbs/__init__.py
cbs/cast.py
cbs/env.py
cbs/settings.py
cbs/urls.py
cbs/version.py
django_classy_settings-3.0.7.dist-info/LICENSE
django_classy_settings-3.0.7.dist-info/METADATA
django_classy_settings-3.0.7.dist-info/WHEEL
django_classy_settings-3.0.7.dist-info/top_level.txt
django_classy_settings-3.0.7.dist-info/RECORD
